{"version":2,"kind":"Article","sha256":"f29665249e14e3df143f1cbfe7ee7c55ad3eaeacf9dddd589ed7443dc68cd3f6","slug":"about","location":"/about.md","dependencies":[],"frontmatter":{"title":"About Me","content_includes_title":false,"numbering":{"title":{"offset":1}},"exports":[{"format":"md","filename":"about.md","url":"/about-c44552308417ae114269929415eb7088.md"}]},"mdast":{"type":"root","children":[{"type":"block","children":[{"type":"paragraph","position":{"start":{"line":3,"column":1},"end":{"line":3,"column":1}},"children":[{"type":"text","value":"I’m a passionate software developer with experience spanning data analysis, scientific computing, virtual reality, and financial technology. I enjoy tackling complex problems across diverse domains, from physics simulations to interactive VR experiences and data-driven applications.","position":{"start":{"line":3,"column":1},"end":{"line":3,"column":1}},"key":"lKR8GXKLtJ"}],"key":"oZmUEHVa2m"},{"type":"heading","depth":2,"position":{"start":{"line":5,"column":1},"end":{"line":5,"column":1}},"children":[{"type":"text","value":"Background","position":{"start":{"line":5,"column":1},"end":{"line":5,"column":1}},"key":"ku2uZTPvOB"}],"identifier":"background","label":"Background","html_id":"background","implicit":true,"key":"vMSbCXobMc"},{"type":"paragraph","position":{"start":{"line":7,"column":1},"end":{"line":7,"column":1}},"children":[{"type":"text","value":"My journey in software development has taken me through various fascinating domains:","position":{"start":{"line":7,"column":1},"end":{"line":7,"column":1}},"key":"fwPYwAXuGx"}],"key":"QEuolodfgc"},{"type":"list","ordered":false,"spread":false,"position":{"start":{"line":9,"column":1},"end":{"line":13,"column":1}},"children":[{"type":"listItem","spread":true,"position":{"start":{"line":9,"column":1},"end":{"line":9,"column":1}},"children":[{"type":"paragraph","children":[{"type":"strong","position":{"start":{"line":9,"column":1},"end":{"line":9,"column":1}},"children":[{"type":"text","value":"Scientific Computing","position":{"start":{"line":9,"column":1},"end":{"line":9,"column":1}},"key":"hp4z2ThfuO"}],"key":"wVYPawvHap"},{"type":"text","value":": Implementing complex physics simulations for superconductor research","position":{"start":{"line":9,"column":1},"end":{"line":9,"column":1}},"key":"zqB9ym7Mhg"}],"key":"MlhZgdeb8G"}],"key":"vmjAqFrom5"},{"type":"listItem","spread":true,"position":{"start":{"line":10,"column":1},"end":{"line":10,"column":1}},"children":[{"type":"paragraph","children":[{"type":"strong","position":{"start":{"line":10,"column":1},"end":{"line":10,"column":1}},"children":[{"type":"text","value":"Data Analysis","position":{"start":{"line":10,"column":1},"end":{"line":10,"column":1}},"key":"txtGCd1F3G"}],"key":"m72MXSpOSM"},{"type":"text","value":": Processing GPS tracking data and financial datasets for insights","position":{"start":{"line":10,"column":1},"end":{"line":10,"column":1}},"key":"OCtF2of20t"}],"key":"oefTxK8EPp"}],"key":"Oa3wYItgFd"},{"type":"listItem","spread":true,"position":{"start":{"line":11,"column":1},"end":{"line":11,"column":1}},"children":[{"type":"paragraph","children":[{"type":"strong","position":{"start":{"line":11,"column":1},"end":{"line":11,"column":1}},"children":[{"type":"text","value":"Virtual Reality","position":{"start":{"line":11,"column":1},"end":{"line":11,"column":1}},"key":"KEqWs2rcOu"}],"key":"SIXAzLO9OF"},{"type":"text","value":": Creating immersive experiences with haptic feedback systems","position":{"start":{"line":11,"column":1},"end":{"line":11,"column":1}},"key":"lZGti2kl67"}],"key":"IHN7oDKpZw"}],"key":"pK9Aq8UNuX"},{"type":"listItem","spread":true,"position":{"start":{"line":12,"column":1},"end":{"line":13,"column":1}},"children":[{"type":"paragraph","children":[{"type":"strong","position":{"start":{"line":12,"column":1},"end":{"line":12,"column":1}},"children":[{"type":"text","value":"Financial Technology","position":{"start":{"line":12,"column":1},"end":{"line":12,"column":1}},"key":"dPdsYXjig7"}],"key":"HZ33NAk2HJ"},{"type":"text","value":": Building tools for personal finance management and analysis","position":{"start":{"line":12,"column":1},"end":{"line":12,"column":1}},"key":"RVAww8gcfK"}],"key":"B6f9kZBJjU"}],"key":"lG4KVDhaEJ"}],"key":"Folq3wclgs"},{"type":"heading","depth":2,"position":{"start":{"line":14,"column":1},"end":{"line":14,"column":1}},"children":[{"type":"text","value":"Technical Expertise","position":{"start":{"line":14,"column":1},"end":{"line":14,"column":1}},"key":"jhnsC84pQD"}],"identifier":"technical-expertise","label":"Technical Expertise","html_id":"technical-expertise","implicit":true,"key":"ayfKedNQkg"},{"type":"heading","depth":3,"position":{"start":{"line":16,"column":1},"end":{"line":16,"column":1}},"children":[{"type":"text","value":"Programming Languages","position":{"start":{"line":16,"column":1},"end":{"line":16,"column":1}},"key":"zwJxWigYse"}],"identifier":"programming-languages","label":"Programming Languages","html_id":"programming-languages","implicit":true,"key":"Mrxf1QayQc"},{"type":"list","ordered":false,"spread":false,"position":{"start":{"line":17,"column":1},"end":{"line":21,"column":1}},"children":[{"type":"listItem","spread":true,"position":{"start":{"line":17,"column":1},"end":{"line":17,"column":1}},"children":[{"type":"paragraph","children":[{"type":"strong","position":{"start":{"line":17,"column":1},"end":{"line":17,"column":1}},"children":[{"type":"text","value":"Python","position":{"start":{"line":17,"column":1},"end":{"line":17,"column":1}},"key":"t4mielgyRl"}],"key":"oMVhYAdwKX"},{"type":"text","value":": Primary language for data analysis, scientific computing, and automation","position":{"start":{"line":17,"column":1},"end":{"line":17,"column":1}},"key":"DdIVs8Npe9"}],"key":"NTDwVSmCUY"}],"key":"x93EfvG6Ib"},{"type":"listItem","spread":true,"position":{"start":{"line":18,"column":1},"end":{"line":18,"column":1}},"children":[{"type":"paragraph","children":[{"type":"strong","position":{"start":{"line":18,"column":1},"end":{"line":18,"column":1}},"children":[{"type":"text","value":"C#","position":{"start":{"line":18,"column":1},"end":{"line":18,"column":1}},"key":"trYFSWZQFg"}],"key":"lCexdiKSmn"},{"type":"text","value":": Unity development and Windows applications","position":{"start":{"line":18,"column":1},"end":{"line":18,"column":1}},"key":"wiWV8PzWLG"}],"key":"p2VePh1LbL"}],"key":"sns6yD559H"},{"type":"listItem","spread":true,"position":{"start":{"line":19,"column":1},"end":{"line":19,"column":1}},"children":[{"type":"paragraph","children":[{"type":"strong","position":{"start":{"line":19,"column":1},"end":{"line":19,"column":1}},"children":[{"type":"text","value":"JavaScript","position":{"start":{"line":19,"column":1},"end":{"line":19,"column":1}},"key":"DStnlxENk2"}],"key":"rGsrMsfMJd"},{"type":"text","value":": Web development and interactive visualizations","position":{"start":{"line":19,"column":1},"end":{"line":19,"column":1}},"key":"PTFS1kaKSW"}],"key":"Qu8SAMUH49"}],"key":"EC6kARGQaz"},{"type":"listItem","spread":true,"position":{"start":{"line":20,"column":1},"end":{"line":21,"column":1}},"children":[{"type":"paragraph","children":[{"type":"strong","position":{"start":{"line":20,"column":1},"end":{"line":20,"column":1}},"children":[{"type":"text","value":"MATLAB","position":{"start":{"line":20,"column":1},"end":{"line":20,"column":1}},"key":"hVrZVZIgGL"}],"key":"RsSfS7TJC8"},{"type":"text","value":": Scientific computing and algorithm development","position":{"start":{"line":20,"column":1},"end":{"line":20,"column":1}},"key":"vbYgIY0BNh"}],"key":"ys1JSGGUkT"}],"key":"RpMuZqWHsx"}],"key":"cLg4bPbpk1"},{"type":"heading","depth":3,"position":{"start":{"line":22,"column":1},"end":{"line":22,"column":1}},"children":[{"type":"text","value":"Frameworks & Libraries","position":{"start":{"line":22,"column":1},"end":{"line":22,"column":1}},"key":"k3XAG7nfXq"}],"identifier":"frameworks-libraries","label":"Frameworks & Libraries","html_id":"frameworks-libraries","implicit":true,"key":"O3zK5JchjJ"},{"type":"list","ordered":false,"spread":false,"position":{"start":{"line":23,"column":1},"end":{"line":27,"column":1}},"children":[{"type":"listItem","spread":true,"position":{"start":{"line":23,"column":1},"end":{"line":23,"column":1}},"children":[{"type":"paragraph","children":[{"type":"strong","position":{"start":{"line":23,"column":1},"end":{"line":23,"column":1}},"children":[{"type":"text","value":"Data Science","position":{"start":{"line":23,"column":1},"end":{"line":23,"column":1}},"key":"ntaaTBjXDK"}],"key":"kzMsf5TNxL"},{"type":"text","value":": Pandas, NumPy, SciPy, Matplotlib, Plotly","position":{"start":{"line":23,"column":1},"end":{"line":23,"column":1}},"key":"tPngumTvqd"}],"key":"YvwIYac3a4"}],"key":"EXUB8Z3zxH"},{"type":"listItem","spread":true,"position":{"start":{"line":24,"column":1},"end":{"line":24,"column":1}},"children":[{"type":"paragraph","children":[{"type":"strong","position":{"start":{"line":24,"column":1},"end":{"line":24,"column":1}},"children":[{"type":"text","value":"Web Development","position":{"start":{"line":24,"column":1},"end":{"line":24,"column":1}},"key":"CXQ5dspVLr"}],"key":"qIiLFtcPYd"},{"type":"text","value":": Streamlit, Flask, HTML/CSS","position":{"start":{"line":24,"column":1},"end":{"line":24,"column":1}},"key":"yUJDOPZFis"}],"key":"b9Ocks9Pd6"}],"key":"gHWQkkvyVW"},{"type":"listItem","spread":true,"position":{"start":{"line":25,"column":1},"end":{"line":25,"column":1}},"children":[{"type":"paragraph","children":[{"type":"strong","position":{"start":{"line":25,"column":1},"end":{"line":25,"column":1}},"children":[{"type":"text","value":"Game Development","position":{"start":{"line":25,"column":1},"end":{"line":25,"column":1}},"key":"CQUpYf6MbD"}],"key":"rjH3OOFbon"},{"type":"text","value":": Unity 3D, SteamVR","position":{"start":{"line":25,"column":1},"end":{"line":25,"column":1}},"key":"IjjxGY3ztd"}],"key":"cGxJzOPFV8"}],"key":"COgiXRH0Nj"},{"type":"listItem","spread":true,"position":{"start":{"line":26,"column":1},"end":{"line":27,"column":1}},"children":[{"type":"paragraph","children":[{"type":"strong","position":{"start":{"line":26,"column":1},"end":{"line":26,"column":1}},"children":[{"type":"text","value":"Scientific Computing","position":{"start":{"line":26,"column":1},"end":{"line":26,"column":1}},"key":"x1oc7ePnIY"}],"key":"rmwmwItjzb"},{"type":"text","value":": Custom numerical solvers and simulation frameworks","position":{"start":{"line":26,"column":1},"end":{"line":26,"column":1}},"key":"eDK8iphHLY"}],"key":"Iuyho7XlVa"}],"key":"tpCxUg4z3f"}],"key":"uOkIvc4Wnw"},{"type":"heading","depth":3,"position":{"start":{"line":28,"column":1},"end":{"line":28,"column":1}},"children":[{"type":"text","value":"Domains of Expertise","position":{"start":{"line":28,"column":1},"end":{"line":28,"column":1}},"key":"x0fxqM9Dgb"}],"identifier":"domains-of-expertise","label":"Domains of Expertise","html_id":"domains-of-expertise","implicit":true,"key":"mzNR2gbfdq"},{"type":"list","ordered":false,"spread":false,"position":{"start":{"line":29,"column":1},"end":{"line":33,"column":1}},"children":[{"type":"listItem","spread":true,"position":{"start":{"line":29,"column":1},"end":{"line":29,"column":1}},"children":[{"type":"paragraph","children":[{"type":"strong","position":{"start":{"line":29,"column":1},"end":{"line":29,"column":1}},"children":[{"type":"text","value":"Data Visualization","position":{"start":{"line":29,"column":1},"end":{"line":29,"column":1}},"key":"VWuzbw8Bjn"}],"key":"vP4cpRzac5"},{"type":"text","value":": Creating clear, interactive charts and dashboards","position":{"start":{"line":29,"column":1},"end":{"line":29,"column":1}},"key":"KmRuJI11nz"}],"key":"fueeHodYKk"}],"key":"NRWEDTkzpN"},{"type":"listItem","spread":true,"position":{"start":{"line":30,"column":1},"end":{"line":30,"column":1}},"children":[{"type":"paragraph","children":[{"type":"strong","position":{"start":{"line":30,"column":1},"end":{"line":30,"column":1}},"children":[{"type":"text","value":"Scientific Simulation","position":{"start":{"line":30,"column":1},"end":{"line":30,"column":1}},"key":"oMiNyEd5ix"}],"key":"LsF4oEqa2G"},{"type":"text","value":": Implementing numerical methods for physics problems","position":{"start":{"line":30,"column":1},"end":{"line":30,"column":1}},"key":"JCHZqBzVLq"}],"key":"nbAa0AIuRo"}],"key":"Pn07pFyywx"},{"type":"listItem","spread":true,"position":{"start":{"line":31,"column":1},"end":{"line":31,"column":1}},"children":[{"type":"paragraph","children":[{"type":"strong","position":{"start":{"line":31,"column":1},"end":{"line":31,"column":1}},"children":[{"type":"text","value":"Virtual Reality","position":{"start":{"line":31,"column":1},"end":{"line":31,"column":1}},"key":"ITjAOP1Zth"}],"key":"X5Y04vG20q"},{"type":"text","value":": Developing immersive experiences with real-world applications","position":{"start":{"line":31,"column":1},"end":{"line":31,"column":1}},"key":"rOodVGtOYv"}],"key":"wfnPyZomiz"}],"key":"ReExcT4Equ"},{"type":"listItem","spread":true,"position":{"start":{"line":32,"column":1},"end":{"line":33,"column":1}},"children":[{"type":"paragraph","children":[{"type":"strong","position":{"start":{"line":32,"column":1},"end":{"line":32,"column":1}},"children":[{"type":"text","value":"Financial Analysis","position":{"start":{"line":32,"column":1},"end":{"line":32,"column":1}},"key":"JdI9fQZMRe"}],"key":"ho8yFmxTBD"},{"type":"text","value":": Building tools for budget tracking and financial insights","position":{"start":{"line":32,"column":1},"end":{"line":32,"column":1}},"key":"ihvFmTz3E7"}],"key":"LFTgP8liaE"}],"key":"cuUBlJHuk3"}],"key":"g69PFx6DZQ"},{"type":"heading","depth":2,"position":{"start":{"line":34,"column":1},"end":{"line":34,"column":1}},"children":[{"type":"text","value":"Education & Research","position":{"start":{"line":34,"column":1},"end":{"line":34,"column":1}},"key":"SS0AeKlWBg"}],"identifier":"education-research","label":"Education & Research","html_id":"education-research","implicit":true,"key":"av8xEofq2j"},{"type":"paragraph","position":{"start":{"line":36,"column":1},"end":{"line":36,"column":1}},"children":[{"type":"text","value":"My academic background includes work in:","position":{"start":{"line":36,"column":1},"end":{"line":36,"column":1}},"key":"feoINdCEYi"}],"key":"PDGj3rRahe"},{"type":"list","ordered":false,"spread":false,"position":{"start":{"line":37,"column":1},"end":{"line":41,"column":1}},"children":[{"type":"listItem","spread":true,"position":{"start":{"line":37,"column":1},"end":{"line":37,"column":1}},"children":[{"type":"paragraph","children":[{"type":"text","value":"Computational physics and materials science","position":{"start":{"line":37,"column":1},"end":{"line":37,"column":1}},"key":"KLGq4PiyV6"}],"key":"Fdq8mCqdzL"}],"key":"OxKgZkT6Nv"},{"type":"listItem","spread":true,"position":{"start":{"line":38,"column":1},"end":{"line":38,"column":1}},"children":[{"type":"paragraph","children":[{"type":"text","value":"Time-dependent simulations of superconducting systems","position":{"start":{"line":38,"column":1},"end":{"line":38,"column":1}},"key":"c2fm2pZyXw"}],"key":"TdRyA3s284"}],"key":"EolUUFxGfQ"},{"type":"listItem","spread":true,"position":{"start":{"line":39,"column":1},"end":{"line":39,"column":1}},"children":[{"type":"paragraph","children":[{"type":"text","value":"Virtual reality interface design and user experience research","position":{"start":{"line":39,"column":1},"end":{"line":39,"column":1}},"key":"jNoarhSFMc"}],"key":"Wla72iZDMS"}],"key":"WmSO7zg4dV"},{"type":"listItem","spread":true,"position":{"start":{"line":40,"column":1},"end":{"line":41,"column":1}},"children":[{"type":"paragraph","children":[{"type":"text","value":"Data analysis methodologies and visualization techniques","position":{"start":{"line":40,"column":1},"end":{"line":40,"column":1}},"key":"jHN3OAsxUS"}],"key":"uE3SmUEycM"}],"key":"GFJttLZhTb"}],"key":"J1wr7dsdTS"},{"type":"heading","depth":2,"position":{"start":{"line":42,"column":1},"end":{"line":42,"column":1}},"children":[{"type":"text","value":"Philosophy","position":{"start":{"line":42,"column":1},"end":{"line":42,"column":1}},"key":"GkJgvIMn4B"}],"identifier":"philosophy","label":"Philosophy","html_id":"philosophy","implicit":true,"key":"CB6tICljGZ"},{"type":"paragraph","position":{"start":{"line":44,"column":1},"end":{"line":44,"column":1}},"children":[{"type":"text","value":"I believe in:","position":{"start":{"line":44,"column":1},"end":{"line":44,"column":1}},"key":"mlZggePGwK"}],"key":"PTx73nJ3Ge"},{"type":"list","ordered":false,"spread":false,"position":{"start":{"line":45,"column":1},"end":{"line":49,"column":1}},"children":[{"type":"listItem","spread":true,"position":{"start":{"line":45,"column":1},"end":{"line":45,"column":1}},"children":[{"type":"paragraph","children":[{"type":"strong","position":{"start":{"line":45,"column":1},"end":{"line":45,"column":1}},"children":[{"type":"text","value":"Clear Documentation","position":{"start":{"line":45,"column":1},"end":{"line":45,"column":1}},"key":"FtfU8DYwgU"}],"key":"hrhfR2L8IR"},{"type":"text","value":": Every project should be well-documented and reproducible","position":{"start":{"line":45,"column":1},"end":{"line":45,"column":1}},"key":"ZxvN8XoFNt"}],"key":"LQlFSnrAYU"}],"key":"xNsULlqVxH"},{"type":"listItem","spread":true,"position":{"start":{"line":46,"column":1},"end":{"line":46,"column":1}},"children":[{"type":"paragraph","children":[{"type":"strong","position":{"start":{"line":46,"column":1},"end":{"line":46,"column":1}},"children":[{"type":"text","value":"User-Centered Design","position":{"start":{"line":46,"column":1},"end":{"line":46,"column":1}},"key":"LProZaoJxf"}],"key":"GueieO5t9D"},{"type":"text","value":": Technology should solve real problems for real people","position":{"start":{"line":46,"column":1},"end":{"line":46,"column":1}},"key":"UDhWPf4ahC"}],"key":"OoaIss79vo"}],"key":"u7OFR6yazw"},{"type":"listItem","spread":true,"position":{"start":{"line":47,"column":1},"end":{"line":47,"column":1}},"children":[{"type":"paragraph","children":[{"type":"strong","position":{"start":{"line":47,"column":1},"end":{"line":47,"column":1}},"children":[{"type":"text","value":"Continuous Learning","position":{"start":{"line":47,"column":1},"end":{"line":47,"column":1}},"key":"mKJTe8iahQ"}],"key":"PMLiG89M3d"},{"type":"text","value":": Staying current with emerging technologies and methodologies","position":{"start":{"line":47,"column":1},"end":{"line":47,"column":1}},"key":"AcCcOwPRb4"}],"key":"AM5F4TnbGx"}],"key":"XUtilsaItt"},{"type":"listItem","spread":true,"position":{"start":{"line":48,"column":1},"end":{"line":49,"column":1}},"children":[{"type":"paragraph","children":[{"type":"strong","position":{"start":{"line":48,"column":1},"end":{"line":48,"column":1}},"children":[{"type":"text","value":"Open Source","position":{"start":{"line":48,"column":1},"end":{"line":48,"column":1}},"key":"v2Rmsq4TiZ"}],"key":"ZOTZIdhjte"},{"type":"text","value":": Sharing knowledge and tools with the broader community","position":{"start":{"line":48,"column":1},"end":{"line":48,"column":1}},"key":"Bu6LsJkLvA"}],"key":"usfGfXFvW0"}],"key":"pnSwUScb1k"}],"key":"TPKvPj1YTV"},{"type":"heading","depth":2,"position":{"start":{"line":50,"column":1},"end":{"line":50,"column":1}},"children":[{"type":"text","value":"Current Interests","position":{"start":{"line":50,"column":1},"end":{"line":50,"column":1}},"key":"PHZVolKFpU"}],"identifier":"current-interests","label":"Current Interests","html_id":"current-interests","implicit":true,"key":"JZvNBGKP7t"},{"type":"paragraph","position":{"start":{"line":52,"column":1},"end":{"line":52,"column":1}},"children":[{"type":"text","value":"I’m currently exploring:","position":{"start":{"line":52,"column":1},"end":{"line":52,"column":1}},"key":"qRADdPHRLS"}],"key":"wU0Lij6g50"},{"type":"list","ordered":false,"spread":false,"position":{"start":{"line":53,"column":1},"end":{"line":57,"column":1}},"children":[{"type":"listItem","spread":true,"position":{"start":{"line":53,"column":1},"end":{"line":53,"column":1}},"children":[{"type":"paragraph","children":[{"type":"text","value":"Advanced visualization techniques for scientific data","position":{"start":{"line":53,"column":1},"end":{"line":53,"column":1}},"key":"ZkqdeNvBpy"}],"key":"F7v9jjZZ1Q"}],"key":"DrhKgp2eNb"},{"type":"listItem","spread":true,"position":{"start":{"line":54,"column":1},"end":{"line":54,"column":1}},"children":[{"type":"paragraph","children":[{"type":"text","value":"Machine learning applications in physics simulations","position":{"start":{"line":54,"column":1},"end":{"line":54,"column":1}},"key":"pZqVyGBDFZ"}],"key":"TfjdK67g3B"}],"key":"VgPe065qLO"},{"type":"listItem","spread":true,"position":{"start":{"line":55,"column":1},"end":{"line":55,"column":1}},"children":[{"type":"paragraph","children":[{"type":"text","value":"Improved user interfaces for VR applications","position":{"start":{"line":55,"column":1},"end":{"line":55,"column":1}},"key":"TfNURO3Q80"}],"key":"uMhbAIKNPP"}],"key":"opcd56JJse"},{"type":"listItem","spread":true,"position":{"start":{"line":56,"column":1},"end":{"line":57,"column":1}},"children":[{"type":"paragraph","children":[{"type":"text","value":"Automated financial analysis and reporting tools","position":{"start":{"line":56,"column":1},"end":{"line":56,"column":1}},"key":"Aa2H3Z6mDk"}],"key":"uaTjfxSN6I"}],"key":"gdh83bTVcr"}],"key":"ktCuf512kv"},{"type":"thematicBreak","position":{"start":{"line":58,"column":1},"end":{"line":58,"column":1}},"key":"ChErXC2rh7"},{"type":"paragraph","position":{"start":{"line":60,"column":1},"end":{"line":60,"column":1}},"children":[{"type":"text","value":"Feel free to explore my projects to see these principles and technologies in action!","position":{"start":{"line":60,"column":1},"end":{"line":60,"column":1}},"key":"xZI9IBQEIU"}],"key":"NtVYXcbG1e"}],"key":"ULMMZtz1lV"}],"key":"FSe3IDo6qB"},"references":{"cite":{"order":[],"data":{}}}}