{"version":2,"kind":"Article","sha256":"3681baa1ad56c652a4b7b2148adf49c497892a31bee5806d2e5383c3fbca688b","slug":"contact","location":"/contact.md","dependencies":[],"frontmatter":{"title":"Contact","content_includes_title":false,"numbering":{"title":{"offset":1}},"exports":[{"format":"md","filename":"contact.md","url":"/contact-e91577318b283370a9a5d998d9a6821e.md"}]},"mdast":{"type":"root","children":[{"type":"block","children":[{"type":"paragraph","position":{"start":{"line":3,"column":1},"end":{"line":3,"column":1}},"children":[{"type":"text","value":"I’m always open to discussing new opportunities, interesting projects, or just having a chat about technology.","position":{"start":{"line":3,"column":1},"end":{"line":3,"column":1}},"key":"Urwc7o7HCU"}],"key":"abhoK8zEbp"},{"type":"heading","depth":2,"position":{"start":{"line":5,"column":1},"end":{"line":5,"column":1}},"children":[{"type":"text","value":"Get In Touch","position":{"start":{"line":5,"column":1},"end":{"line":5,"column":1}},"key":"kGf6N99IjB"}],"identifier":"get-in-touch","label":"Get In Touch","html_id":"get-in-touch","implicit":true,"key":"axYWgPcIdQ"},{"type":"mystDirective","name":"panels","value":"Email\n^^^\n[![Email](https://img.shields.io/badge/Email-your.email@example.com-blue?style=for-the-badge&logo=gmail)](mailto:your.email@example.com)\n\n---\n\nGitHub\n^^^\n[![GitHub](https://img.shields.io/badge/GitHub-omedeiro-black?style=for-the-badge&logo=github)](https://github.com/omedeiro)\n\n---\n\nLinkedIn  \n^^^\n[![LinkedIn](https://img.shields.io/badge/LinkedIn-Connect-blue?style=for-the-badge&logo=linkedin)](https://linkedin.com/in/yourprofile)","position":{"start":{"line":7,"column":1},"end":{"line":23,"column":1}},"key":"pqwRG5y2VR"},{"type":"heading","depth":2,"position":{"start":{"line":25,"column":1},"end":{"line":25,"column":1}},"children":[{"type":"text","value":"Areas of Interest","position":{"start":{"line":25,"column":1},"end":{"line":25,"column":1}},"key":"EC9Tsz42iW"}],"identifier":"areas-of-interest","label":"Areas of Interest","html_id":"areas-of-interest","implicit":true,"key":"Wx0TUdbi6J"},{"type":"paragraph","position":{"start":{"line":27,"column":1},"end":{"line":27,"column":1}},"children":[{"type":"text","value":"I’m particularly interested in discussing:","position":{"start":{"line":27,"column":1},"end":{"line":27,"column":1}},"key":"bHO3dhinp6"}],"key":"noa456yaCY"},{"type":"list","ordered":false,"spread":false,"position":{"start":{"line":29,"column":1},"end":{"line":34,"column":1}},"children":[{"type":"listItem","spread":true,"position":{"start":{"line":29,"column":1},"end":{"line":29,"column":1}},"children":[{"type":"paragraph","children":[{"type":"strong","position":{"start":{"line":29,"column":1},"end":{"line":29,"column":1}},"children":[{"type":"text","value":"Data Science Projects","position":{"start":{"line":29,"column":1},"end":{"line":29,"column":1}},"key":"AJB586nMNJ"}],"key":"HO9rq16jNd"},{"type":"text","value":": Analysis, visualization, and insights from complex datasets","position":{"start":{"line":29,"column":1},"end":{"line":29,"column":1}},"key":"cB1IObkc18"}],"key":"ptWk4YMadY"}],"key":"MtafuNNAMW"},{"type":"listItem","spread":true,"position":{"start":{"line":30,"column":1},"end":{"line":30,"column":1}},"children":[{"type":"paragraph","children":[{"type":"strong","position":{"start":{"line":30,"column":1},"end":{"line":30,"column":1}},"children":[{"type":"text","value":"Scientific Computing","position":{"start":{"line":30,"column":1},"end":{"line":30,"column":1}},"key":"uc5t1QgxbT"}],"key":"qKtxfjyNx1"},{"type":"text","value":": Numerical methods, simulations, and research collaborations","position":{"start":{"line":30,"column":1},"end":{"line":30,"column":1}},"key":"wpw7netD92"}],"key":"WVyJVKfezt"}],"key":"oSpxYmCe3X"},{"type":"listItem","spread":true,"position":{"start":{"line":31,"column":1},"end":{"line":31,"column":1}},"children":[{"type":"paragraph","children":[{"type":"strong","position":{"start":{"line":31,"column":1},"end":{"line":31,"column":1}},"children":[{"type":"text","value":"VR/AR Development","position":{"start":{"line":31,"column":1},"end":{"line":31,"column":1}},"key":"V35gsAnNJR"}],"key":"Bls4DXb5Q5"},{"type":"text","value":": Immersive experiences and innovative interface design","position":{"start":{"line":31,"column":1},"end":{"line":31,"column":1}},"key":"S68GQ03GGZ"}],"key":"ZWAtKt0kYs"}],"key":"P5ib4fdeuA"},{"type":"listItem","spread":true,"position":{"start":{"line":32,"column":1},"end":{"line":32,"column":1}},"children":[{"type":"paragraph","children":[{"type":"strong","position":{"start":{"line":32,"column":1},"end":{"line":32,"column":1}},"children":[{"type":"text","value":"Open Source Contributions","position":{"start":{"line":32,"column":1},"end":{"line":32,"column":1}},"key":"tU1ESvvAU5"}],"key":"ype1AQLPUh"},{"type":"text","value":": Collaborative development and knowledge sharing","position":{"start":{"line":32,"column":1},"end":{"line":32,"column":1}},"key":"bKY5k13PcC"}],"key":"L3UrN6Wwqn"}],"key":"Xl1M8bOmu5"},{"type":"listItem","spread":true,"position":{"start":{"line":33,"column":1},"end":{"line":34,"column":1}},"children":[{"type":"paragraph","children":[{"type":"strong","position":{"start":{"line":33,"column":1},"end":{"line":33,"column":1}},"children":[{"type":"text","value":"Career Opportunities","position":{"start":{"line":33,"column":1},"end":{"line":33,"column":1}},"key":"RxFA1llqky"}],"key":"xpHPANjkzE"},{"type":"text","value":": Roles in data science, scientific computing, or software development","position":{"start":{"line":33,"column":1},"end":{"line":33,"column":1}},"key":"hYVyK22fS0"}],"key":"xNdtmrIy7m"}],"key":"s6NVksl5tg"}],"key":"eE3Jj8TIL2"},{"type":"heading","depth":2,"position":{"start":{"line":35,"column":1},"end":{"line":35,"column":1}},"children":[{"type":"text","value":"Response Time","position":{"start":{"line":35,"column":1},"end":{"line":35,"column":1}},"key":"f6hC9UVHXz"}],"identifier":"response-time","label":"Response Time","html_id":"response-time","implicit":true,"key":"PnqpxYHB9A"},{"type":"paragraph","position":{"start":{"line":37,"column":1},"end":{"line":37,"column":1}},"children":[{"type":"text","value":"I typically respond to emails within 24-48 hours. For urgent matters, please mention “URGENT” in the subject line.","position":{"start":{"line":37,"column":1},"end":{"line":37,"column":1}},"key":"v8zYJIV2XE"}],"key":"QfFEnkv5bD"},{"type":"heading","depth":2,"position":{"start":{"line":39,"column":1},"end":{"line":39,"column":1}},"children":[{"type":"text","value":"Collaboration","position":{"start":{"line":39,"column":1},"end":{"line":39,"column":1}},"key":"HlJwkZBs6v"}],"identifier":"collaboration","label":"Collaboration","html_id":"collaboration","implicit":true,"key":"q94cEvobcK"},{"type":"paragraph","position":{"start":{"line":41,"column":1},"end":{"line":41,"column":1}},"children":[{"type":"text","value":"I’m open to:","position":{"start":{"line":41,"column":1},"end":{"line":41,"column":1}},"key":"Lm7yQ0hsxI"}],"key":"LfuB1qKeSw"},{"type":"list","ordered":false,"spread":false,"position":{"start":{"line":42,"column":1},"end":{"line":46,"column":1}},"children":[{"type":"listItem","spread":true,"position":{"start":{"line":42,"column":1},"end":{"line":42,"column":1}},"children":[{"type":"paragraph","children":[{"type":"strong","position":{"start":{"line":42,"column":1},"end":{"line":42,"column":1}},"children":[{"type":"text","value":"Research Collaborations","position":{"start":{"line":42,"column":1},"end":{"line":42,"column":1}},"key":"KozFXjAieH"}],"key":"h94cHv2pdA"},{"type":"text","value":": Academic or industrial research projects","position":{"start":{"line":42,"column":1},"end":{"line":42,"column":1}},"key":"uwdOFCMcLK"}],"key":"gS5qPqc4cS"}],"key":"DmTAdns3mi"},{"type":"listItem","spread":true,"position":{"start":{"line":43,"column":1},"end":{"line":43,"column":1}},"children":[{"type":"paragraph","children":[{"type":"strong","position":{"start":{"line":43,"column":1},"end":{"line":43,"column":1}},"children":[{"type":"text","value":"Open Source Contributions","position":{"start":{"line":43,"column":1},"end":{"line":43,"column":1}},"key":"og0KBcBl0a"}],"key":"f10Dx7z3Z9"},{"type":"text","value":": Contributing to existing projects or starting new ones","position":{"start":{"line":43,"column":1},"end":{"line":43,"column":1}},"key":"vWJr0EO71T"}],"key":"QzQ94Sdh8o"}],"key":"onCHrKReFF"},{"type":"listItem","spread":true,"position":{"start":{"line":44,"column":1},"end":{"line":44,"column":1}},"children":[{"type":"paragraph","children":[{"type":"strong","position":{"start":{"line":44,"column":1},"end":{"line":44,"column":1}},"children":[{"type":"text","value":"Consulting","position":{"start":{"line":44,"column":1},"end":{"line":44,"column":1}},"key":"icKv70ATYQ"}],"key":"IUNcUGHHfg"},{"type":"text","value":": Short-term projects in my areas of expertise","position":{"start":{"line":44,"column":1},"end":{"line":44,"column":1}},"key":"E1Mgh5p75v"}],"key":"bx7KyOSmQ3"}],"key":"IJwHocHsSM"},{"type":"listItem","spread":true,"position":{"start":{"line":45,"column":1},"end":{"line":46,"column":1}},"children":[{"type":"paragraph","children":[{"type":"strong","position":{"start":{"line":45,"column":1},"end":{"line":45,"column":1}},"children":[{"type":"text","value":"Speaking Engagements","position":{"start":{"line":45,"column":1},"end":{"line":45,"column":1}},"key":"FaMaRSTvrp"}],"key":"WHSSYhlnSb"},{"type":"text","value":": Technical talks or presentations","position":{"start":{"line":45,"column":1},"end":{"line":45,"column":1}},"key":"znurQv4eeJ"}],"key":"iYja5SiB8M"}],"key":"NoXcQSWoww"}],"key":"JUSSLraVev"},{"type":"thematicBreak","position":{"start":{"line":47,"column":1},"end":{"line":47,"column":1}},"key":"JQn4BUBJc4"},{"type":"paragraph","position":{"start":{"line":49,"column":1},"end":{"line":49,"column":1}},"children":[{"type":"emphasis","position":{"start":{"line":49,"column":1},"end":{"line":49,"column":1}},"children":[{"type":"text","value":"Looking forward to connecting with you!","position":{"start":{"line":49,"column":1},"end":{"line":49,"column":1}},"key":"zVupiMDHoE"}],"key":"IeDwYnd7tD"}],"key":"vF66TPgo9l"}],"key":"DOLbxzIjwF"}],"key":"spq0Nd0uHc"},"references":{"cite":{"order":[],"data":{}}}}